twdensity/__init__.py
twdensity/cli.py
twdensity-0.1.0.dist-info/entry_points.txt
twdensity-0.1.0.dist-info/WHEEL
twdensity-0.1.0.dist-info/METADATA
twdensity-0.1.0.dist-info/licenses/LICENSE
twdensity-0.1.0.dist-info/RECORD
