Metadata-Version: 2.1
Name: twdensity
Version: 0.1.0
Summary: Update TaskWarrior task urgency based on the density of task dues in time
License: GPL-3.0
Author-email: Federico Simonetta <22996003+00sapo@users.noreply.github.com>
Requires-Python: >=3.11
